pygments_style_soft_era/__init__.py
pygments_style_soft_era/soft_era.py
pygments_style_soft_era-1.0.3.dist-info/METADATA
pygments_style_soft_era-1.0.3.dist-info/WHEEL
pygments_style_soft_era-1.0.3.dist-info/entry_points.txt
pygments_style_soft_era-1.0.3.dist-info/top_level.txt
pygments_style_soft_era-1.0.3.dist-info/RECORD
