Metadata-Version: 2.1
Name: pygments-style-soft-era
Version: 1.0.3
Summary: Pygments version of the soft-era theme.
Home-page: UNKNOWN
Author: Audrey Moon
Maintainer: GinShio
Maintainer-email: ginshio78@gmail.com
License: MIT
Download-URL: https://github.com/GinShio/pygments
Keywords: pygments,style,soft-era
Platform: UNKNOWN
Classifier: Development Status :: 4 - Beta
Classifier: Environment :: Plugins
Classifier: Intended Audience :: Developers
Classifier: License :: OSI Approved :: MIT License
Classifier: Operating System :: OS Independent
Classifier: Programming Language :: Python
Classifier: Programming Language :: Python :: 2
Classifier: Programming Language :: Python :: 3
Classifier: Topic :: Software Development :: Libraries :: Python Modules
Requires-Dist: pygments (>=1.5)
